[{"time": 1603065600, "high": 0.1374, "low": 0.1374, "open": 0.1346, "volumefrom": 0, "volumeto": 0, "close": 0.1374, "conversionType": "multiply", "conversionSymbol": "BTC"}, {"time": 1603152000, "high": 0.1394, "low": 0.07725, "open": 0.1374, "volumefrom": 206, "volumeto": 15.91, "close": 0.07725, "conversionType": "multiply", "conversionSymbol": "BTC"}, {"time": 1603238400, "high": 0.08303, "low": 0.08303, "open": 0.07725, "volumefrom": 0, "volumeto": 0, "close": 0.08303, "conversionType": "multiply", "conversionSymbol": "BTC"}, {"time": 1603324800, "high": 0.08418, "low": 0.08418, "open": 0.08303, "volumefrom": 0, "volumeto": 0, "close": 0.08418, "conversionType": "multiply", "conversionSymbol": "BTC"}, {"time": 1603411200, "high": 0.08383, "low": 0.08383, "open": 0.08418, "volumefrom": 0, "volumeto": 0, "close": 0.08383, "conversionType": "multiply", "conversionSymbol": "BTC"}, {"time": 1603497600, "high": 0.08506, "low": 0.08506, "open": 0.08383, "volumefrom": 0, "volumeto": 0, "close": 0.08506, "conversionType": "multiply", "conversionSymbol": "BTC"}, {"time": 1603584000, "high": 0.08451, "low": 0.07303, "open": 0.08506, "volumefrom": 9, "volumeto": 0.6573, "close": 0.07303, "conversionType": "multiply", "conversionSymbol": "BTC"}, {"time": 1603670400, "high": 0.1212, "low": 0.07319, "open": 0.07303, "volumefrom": 124, "volumeto": 15.02, "close": 0.1212, "conversionType": "multiply", "conversionSymbol": "BTC"}, {"time": 1603756800, "high": 0.1265, "low": 0.1265, "open": 0.1212, "volumefrom": 0, "volumeto": 0, "close": 0.1265, "conversionType": "multiply", "conversionSymbol": "BTC"}, {"time": 1603843200, "high": 0.1232, "low": 0.1232, "open": 0.1265, "volumefrom": 0, "volumeto": 0, "close": 0.1232, "conversionType": "multiply", "conversionSymbol": "BTC"}, {"time": 1603929600, "high": 0.1248, "low": 0.1248, "open": 0.1232, "volumefrom": 0, "volumeto": 0, "close": 0.1248, "conversionType": "multiply", "conversionSymbol": "BTC"}, {"time": 1604016000, "high": 0.1258, "low": 0.1258, "open": 0.1248, "volumefrom": 0, "volumeto": 0, "close": 0.1258, "conversionType": "multiply", "conversionSymbol": "BTC"}, {"time": 1604102400, "high": 0.128, "low": 0.128, "open": 0.1258, "volumefrom": 0, "volumeto": 0, "close": 0.128, "conversionType": "multiply", "conversionSymbol": "BTC"}, {"time": 1604188800, "high": 0.1276, "low": 0.09798, "open": 0.128, "volumefrom": 135, "volumeto": 13.23, "close": 0.09798, "conversionType": "multiply", "conversionSymbol": "BTC"}, {"time": 1604275200, "high": 0.1247, "low": 0.09663, "open": 0.09798, "volumefrom": 5, "volumeto": 0.6236, "close": 0.1247, "conversionType": "multiply", "conversionSymbol": "BTC"}, {"time": 1604361600, "high": 0.1289, "low": 0.1289, "open": 0.1247, "volumefrom": 0, "volumeto": 0, "close": 0.1289, "conversionType": "multiply", "conversionSymbol": "BTC"}, {"time": 1604448000, "high": 0.1301, "low": 0.1301, "open": 0.1289, "volumefrom": 0, "volumeto": 0, "close": 0.1301, "conversionType": "multiply", "conversionSymbol": "BTC"}, {"time": 1604534400, "high": 0.1434, "low": 0.1434, "open": 0.1301, "volumefrom": 0, "volumeto": 0, "close": 0.1434, "conversionType": "multiply", "conversionSymbol": "BTC"}, {"time": 1604620800, "high": 0.1433, "low": 0.1433, "open": 0.1434, "volumefrom": 0, "volumeto": 0, "close": 0.1433, "conversionType": "multiply", "conversionSymbol": "BTC"}, {"time": 1604707200, "high": 0.1364, "low": 0.1364, "open": 0.1433, "volumefrom": 0, "volumeto": 0, "close": 0.1364, "conversionType": "multiply", "conversionSymbol": "BTC"}, {"time": 1604793600, "high": 0.1423, "low": 0.1423, "open": 0.1364, "volumefrom": 0, "volumeto": 0, "close": 0.1423, "conversionType": "multiply", "conversionSymbol": "BTC"}, {"time": 1604880000, "high": 0.1409, "low": 0.132, "open": 0.1423, "volumefrom": 9, "volumeto": 1.188, "close": 0.132, "conversionType": "multiply", "conversionSymbol": "BTC"}, {"time": 1604966400, "high": 0.1319, "low": 0.1319, "open": 0.132, "volumefrom": 0, "volumeto": 0, "close": 0.1319, "conversionType": "multiply", "conversionSymbol": "BTC"}, {"time": 1605052800, "high": 0.1352, "low": 0.1352, "open": 0.1319, "volumefrom": 0, "volumeto": 0, "close": 0.1352, "conversionType": "multiply", "conversionSymbol": "BTC"}, {"time": 1605139200, "high": 0.1404, "low": 0.1404, "open": 0.1352, "volumefrom": 0, "volumeto": 0, "close": 0.1404, "conversionType": "multiply", "conversionSymbol": "BTC"}, {"time": 1605225600, "high": 0.1406, "low": 0.1406, "open": 0.1404, "volumefrom": 0, "volumeto": 0, "close": 0.1406, "conversionType": "multiply", "conversionSymbol": "BTC"}, {"time": 1605312000, "high": 0.1384, "low": 0.1384, "open": 0.1406, "volumefrom": 0, "volumeto": 0, "close": 0.1384, "conversionType": "multiply", "conversionSymbol": "BTC"}, {"time": 1605398400, "high": 0.1375, "low": 0.1375, "open": 0.1384, "volumefrom": 0, "volumeto": 0, "close": 0.1375, "conversionType": "multiply", "conversionSymbol": "BTC"}, {"time": 1605484800, "high": 0.144, "low": 0.144, "open": 0.1375, "volumefrom": 0, "volumeto": 0, "close": 0.144, "conversionType": "multiply", "conversionSymbol": "BTC"}, {"time": 1605571200, "high": 0.1522, "low": 0.1522, "open": 0.144, "volumefrom": 0, "volumeto": 0, "close": 0.1522, "conversionType": "multiply", "conversionSymbol": "BTC"}, {"time": 1605657600, "high": 0.1576, "low": 0.1522, "open": 0.1522, "volumefrom": 0, "volumeto": 0, "close": 0.1576, "conversionType": "multiply", "conversionSymbol": "BTC"}]