[{"time": 1603065600, "high": 4.702, "low": 4.702, "open": 4.604, "volumefrom": 0, "volumeto": 0, "close": 4.702, "conversionType": "multiply", "conversionSymbol": "BTC"}, {"time": 1603152000, "high": 4.768, "low": 4.768, "open": 4.702, "volumefrom": 0, "volumeto": 0, "close": 4.768, "conversionType": "multiply", "conversionSymbol": "BTC"}, {"time": 1603238400, "high": 5.124, "low": 5.124, "open": 4.768, "volumefrom": 0, "volumeto": 0, "close": 5.124, "conversionType": "multiply", "conversionSymbol": "BTC"}, {"time": 1603324800, "high": 5.195, "low": 5.195, "open": 5.124, "volumefrom": 0, "volumeto": 0, "close": 5.195, "conversionType": "multiply", "conversionSymbol": "BTC"}, {"time": 1603411200, "high": 5.174, "low": 5.174, "open": 5.195, "volumefrom": 0, "volumeto": 0, "close": 5.174, "conversionType": "multiply", "conversionSymbol": "BTC"}, {"time": 1603497600, "high": 5.249, "low": 5.249, "open": 5.174, "volumefrom": 0, "volumeto": 0, "close": 5.249, "conversionType": "multiply", "conversionSymbol": "BTC"}, {"time": 1603584000, "high": 5.215, "low": 5.215, "open": 5.249, "volumefrom": 0, "volumeto": 0, "close": 5.215, "conversionType": "multiply", "conversionSymbol": "BTC"}, {"time": 1603670400, "high": 5.226, "low": 5.226, "open": 5.215, "volumefrom": 0, "volumeto": 0, "close": 5.226, "conversionType": "multiply", "conversionSymbol": "BTC"}, {"time": 1603756800, "high": 5.457, "low": 5.457, "open": 5.226, "volumefrom": 0, "volumeto": 0, "close": 5.457, "conversionType": "multiply", "conversionSymbol": "BTC"}, {"time": 1603843200, "high": 5.313, "low": 5.313, "open": 5.457, "volumefrom": 0, "volumeto": 0, "close": 5.313, "conversionType": "multiply", "conversionSymbol": "BTC"}, {"time": 1603929600, "high": 5.384, "low": 5.384, "open": 5.313, "volumefrom": 0, "volumeto": 0, "close": 5.384, "conversionType": "multiply", "conversionSymbol": "BTC"}, {"time": 1604016000, "high": 5.425, "low": 5.425, "open": 5.384, "volumefrom": 0, "volumeto": 0, "close": 5.425, "conversionType": "multiply", "conversionSymbol": "BTC"}, {"time": 1604102400, "high": 5.52, "low": 5.52, "open": 5.425, "volumefrom": 0, "volumeto": 0, "close": 5.52, "conversionType": "multiply", "conversionSymbol": "BTC"}, {"time": 1604188800, "high": 5.503, "low": 5.503, "open": 5.52, "volumefrom": 0, "volumeto": 0, "close": 5.503, "conversionType": "multiply", "conversionSymbol": "BTC"}, {"time": 1604275200, "high": 5.427, "low": 5.427, "open": 5.503, "volumefrom": 0, "volumeto": 0, "close": 5.427, "conversionType": "multiply", "conversionSymbol": "BTC"}, {"time": 1604361600, "high": 5.608, "low": 5.608, "open": 5.427, "volumefrom": 0, "volumeto": 0, "close": 5.608, "conversionType": "multiply", "conversionSymbol": "BTC"}, {"time": 1604448000, "high": 5.662, "low": 5.662, "open": 5.608, "volumefrom": 0, "volumeto": 0, "close": 5.662, "conversionType": "multiply", "conversionSymbol": "BTC"}, {"time": 1604534400, "high": 6.238, "low": 6.238, "open": 5.662, "volumefrom": 0, "volumeto": 0, "close": 6.238, "conversionType": "multiply", "conversionSymbol": "BTC"}, {"time": 1604620800, "high": 6.235, "low": 6.235, "open": 6.238, "volumefrom": 0, "volumeto": 0, "close": 6.235, "conversionType": "multiply", "conversionSymbol": "BTC"}, {"time": 1604707200, "high": 5.934, "low": 5.934, "open": 6.235, "volumefrom": 0, "volumeto": 0, "close": 5.934, "conversionType": "multiply", "conversionSymbol": "BTC"}, {"time": 1604793600, "high": 6.194, "low": 6.194, "open": 5.934, "volumefrom": 0, "volumeto": 0, "close": 6.194, "conversionType": "multiply", "conversionSymbol": "BTC"}, {"time": 1604880000, "high": 6.132, "low": 6.132, "open": 6.194, "volumefrom": 0, "volumeto": 0, "close": 6.132, "conversionType": "multiply", "conversionSymbol": "BTC"}, {"time": 1604966400, "high": 6.124, "low": 6.124, "open": 6.132, "volumefrom": 0, "volumeto": 0, "close": 6.124, "conversionType": "multiply", "conversionSymbol": "BTC"}, {"time": 1605052800, "high": 6.281, "low": 6.281, "open": 6.124, "volumefrom": 0, "volumeto": 0, "close": 6.281, "conversionType": "multiply", "conversionSymbol": "BTC"}, {"time": 1605139200, "high": 6.521, "low": 6.521, "open": 6.281, "volumefrom": 0, "volumeto": 0, "close": 6.521, "conversionType": "multiply", "conversionSymbol": "BTC"}, {"time": 1605225600, "high": 6.532, "low": 6.532, "open": 6.521, "volumefrom": 0, "volumeto": 0, "close": 6.532, "conversionType": "multiply", "conversionSymbol": "BTC"}, {"time": 1605312000, "high": 6.429, "low": 6.429, "open": 6.532, "volumefrom": 0, "volumeto": 0, "close": 6.429, "conversionType": "multiply", "conversionSymbol": "BTC"}, {"time": 1605398400, "high": 6.384, "low": 6.384, "open": 6.429, "volumefrom": 0, "volumeto": 0, "close": 6.384, "conversionType": "multiply", "conversionSymbol": "BTC"}, {"time": 1605484800, "high": 6.687, "low": 6.687, "open": 6.384, "volumefrom": 0, "volumeto": 0, "close": 6.687, "conversionType": "multiply", "conversionSymbol": "BTC"}, {"time": 1605571200, "high": 7.071, "low": 7.071, "open": 6.687, "volumefrom": 0, "volumeto": 0, "close": 7.071, "conversionType": "multiply", "conversionSymbol": "BTC"}, {"time": 1605657600, "high": 7.071, "low": 0.0001783, "open": 7.071, "volumefrom": 0, "volumeto": 0, "close": 0.0001783, "conversionType": "multiply", "conversionSymbol": "BTC"}]