[{"time": 1605673380, "high": 0.07391, "low": 0.07391, "open": 0.07374, "volumefrom": 0, "volumeto": 0, "close": 0.07391, "conversionType": "multiply", "conversionSymbol": "ETH"}, {"time": 1605673440, "high": 0.07381, "low": 0.07381, "open": 0.07391, "volumefrom": 0, "volumeto": 0, "close": 0.07381, "conversionType": "multiply", "conversionSymbol": "ETH"}, {"time": 1605673500, "high": 0.07389, "low": 0.07389, "open": 0.07381, "volumefrom": 0, "volumeto": 0, "close": 0.07389, "conversionType": "multiply", "conversionSymbol": "ETH"}, {"time": 1605673560, "high": 0.07382, "low": 0.07382, "open": 0.07389, "volumefrom": 0, "volumeto": 0, "close": 0.07382, "conversionType": "multiply", "conversionSymbol": "ETH"}, {"time": 1605673620, "high": 0.07391, "low": 0.07391, "open": 0.07382, "volumefrom": 0, "volumeto": 0, "close": 0.07391, "conversionType": "multiply", "conversionSymbol": "ETH"}, {"time": 1605673680, "high": 0.07392, "low": 0.07392, "open": 0.07391, "volumefrom": 0, "volumeto": 0, "close": 0.07392, "conversionType": "multiply", "conversionSymbol": "ETH"}, {"time": 1605673740, "high": 0.07391, "low": 0.07391, "open": 0.07392, "volumefrom": 0, "volumeto": 0, "close": 0.07391, "conversionType": "multiply", "conversionSymbol": "ETH"}, {"time": 1605673800, "high": 0.07397, "low": 0.07397, "open": 0.07391, "volumefrom": 0, "volumeto": 0, "close": 0.07397, "conversionType": "multiply", "conversionSymbol": "ETH"}, {"time": 1605673860, "high": 0.07401, "low": 0.07401, "open": 0.07397, "volumefrom": 0, "volumeto": 0, "close": 0.07401, "conversionType": "multiply", "conversionSymbol": "ETH"}, {"time": 1605673920, "high": 0.07398, "low": 0.07398, "open": 0.07401, "volumefrom": 0, "volumeto": 0, "close": 0.07398, "conversionType": "multiply", "conversionSymbol": "ETH"}, {"time": 1605673980, "high": 0.07398, "low": 0.07398, "open": 0.07398, "volumefrom": 0, "volumeto": 0, "close": 0.07398, "conversionType": "multiply", "conversionSymbol": "ETH"}, {"time": 1605674040, "high": 0.0739, "low": 0.0739, "open": 0.07398, "volumefrom": 0, "volumeto": 0, "close": 0.0739, "conversionType": "multiply", "conversionSymbol": "ETH"}, {"time": 1605674100, "high": 0.07383, "low": 0.07383, "open": 0.0739, "volumefrom": 0, "volumeto": 0, "close": 0.07383, "conversionType": "multiply", "conversionSymbol": "ETH"}, {"time": 1605674160, "high": 0.07385, "low": 0.07385, "open": 0.07383, "volumefrom": 0, "volumeto": 0, "close": 0.07385, "conversionType": "multiply", "conversionSymbol": "ETH"}, {"time": 1605674220, "high": 0.0739, "low": 0.0739, "open": 0.07385, "volumefrom": 0, "volumeto": 0, "close": 0.0739, "conversionType": "multiply", "conversionSymbol": "ETH"}, {"time": 1605674280, "high": 0.0739, "low": 0.0739, "open": 0.0739, "volumefrom": 0, "volumeto": 0, "close": 0.0739, "conversionType": "multiply", "conversionSymbol": "ETH"}, {"time": 1605674340, "high": 0.07391, "low": 0.07391, "open": 0.0739, "volumefrom": 0, "volumeto": 0, "close": 0.07391, "conversionType": "multiply", "conversionSymbol": "ETH"}, {"time": 1605674400, "high": 0.07396, "low": 0.07396, "open": 0.07391, "volumefrom": 0, "volumeto": 0, "close": 0.07396, "conversionType": "multiply", "conversionSymbol": "ETH"}, {"time": 1605674460, "high": 0.07406, "low": 0.07406, "open": 0.07396, "volumefrom": 0, "volumeto": 0, "close": 0.07406, "conversionType": "multiply", "conversionSymbol": "ETH"}, {"time": 1605674520, "high": 0.07399, "low": 0.07399, "open": 0.07406, "volumefrom": 0, "volumeto": 0, "close": 0.07399, "conversionType": "multiply", "conversionSymbol": "ETH"}, {"time": 1605674580, "high": 0.07407, "low": 0.07407, "open": 0.07399, "volumefrom": 0, "volumeto": 0, "close": 0.07407, "conversionType": "multiply", "conversionSymbol": "ETH"}, {"time": 1605674640, "high": 0.07408, "low": 0.07408, "open": 0.07407, "volumefrom": 0, "volumeto": 0, "close": 0.07408, "conversionType": "multiply", "conversionSymbol": "ETH"}, {"time": 1605674700, "high": 0.07395, "low": 0.07395, "open": 0.07408, "volumefrom": 0, "volumeto": 0, "close": 0.07395, "conversionType": "multiply", "conversionSymbol": "ETH"}, {"time": 1605674760, "high": 0.07389, "low": 0.07389, "open": 0.07395, "volumefrom": 0, "volumeto": 0, "close": 0.07389, "conversionType": "multiply", "conversionSymbol": "ETH"}, {"time": 1605674820, "high": 0.07391, "low": 0.07391, "open": 0.07389, "volumefrom": 0, "volumeto": 0, "close": 0.07391, "conversionType": "multiply", "conversionSymbol": "ETH"}, {"time": 1605674880, "high": 0.07392, "low": 0.07392, "open": 0.07391, "volumefrom": 0, "volumeto": 0, "close": 0.07392, "conversionType": "multiply", "conversionSymbol": "ETH"}, {"time": 1605674940, "high": 0.07403, "low": 0.07403, "open": 0.07392, "volumefrom": 0, "volumeto": 0, "close": 0.07403, "conversionType": "multiply", "conversionSymbol": "ETH"}, {"time": 1605675000, "high": 0.07401, "low": 0.07401, "open": 0.07403, "volumefrom": 0, "volumeto": 0, "close": 0.07401, "conversionType": "multiply", "conversionSymbol": "ETH"}, {"time": 1605675060, "high": 0.07398, "low": 0.07398, "open": 0.07401, "volumefrom": 0, "volumeto": 0, "close": 0.07398, "conversionType": "multiply", "conversionSymbol": "ETH"}, {"time": 1605675120, "high": 0.07408, "low": 0.07408, "open": 0.07398, "volumefrom": 0, "volumeto": 0, "close": 0.07408, "conversionType": "multiply", "conversionSymbol": "ETH"}, {"time": 1605675180, "high": 0.07403, "low": 0.07403, "open": 0.07408, "volumefrom": 0, "volumeto": 0, "close": 0.07403, "conversionType": "multiply", "conversionSymbol": "ETH"}, {"time": 1605675240, "high": 0.07418, "low": 0.07418, "open": 0.07403, "volumefrom": 0, "volumeto": 0, "close": 0.07418, "conversionType": "multiply", "conversionSymbol": "ETH"}, {"time": 1605675300, "high": 0.07415, "low": 0.07415, "open": 0.07418, "volumefrom": 0, "volumeto": 0, "close": 0.07415, "conversionType": "multiply", "conversionSymbol": "ETH"}, {"time": 1605675360, "high": 0.07407, "low": 0.07407, "open": 0.07415, "volumefrom": 0, "volumeto": 0, "close": 0.07407, "conversionType": "multiply", "conversionSymbol": "ETH"}, {"time": 1605675420, "high": 0.07403, "low": 0.07403, "open": 0.07407, "volumefrom": 0, "volumeto": 0, "close": 0.07403, "conversionType": "multiply", "conversionSymbol": "ETH"}, {"time": 1605675480, "high": 0.07403, "low": 0.07403, "open": 0.07403, "volumefrom": 0, "volumeto": 0, "close": 0.07403, "conversionType": "multiply", "conversionSymbol": "ETH"}, {"time": 1605675540, "high": 0.07408, "low": 0.07408, "open": 0.07403, "volumefrom": 0, "volumeto": 0, "close": 0.07408, "conversionType": "multiply", "conversionSymbol": "ETH"}, {"time": 1605675600, "high": 0.07407, "low": 0.07407, "open": 0.07408, "volumefrom": 0, "volumeto": 0, "close": 0.07407, "conversionType": "multiply", "conversionSymbol": "ETH"}, {"time": 1605675660, "high": 0.074, "low": 0.074, "open": 0.07407, "volumefrom": 0, "volumeto": 0, "close": 0.074, "conversionType": "multiply", "conversionSymbol": "ETH"}, {"time": 1605675720, "high": 0.07382, "low": 0.07382, "open": 0.074, "volumefrom": 0, "volumeto": 0, "close": 0.07382, "conversionType": "multiply", "conversionSymbol": "ETH"}, {"time": 1605675780, "high": 0.07373, "low": 0.07373, "open": 0.07382, "volumefrom": 0, "volumeto": 0, "close": 0.07373, "conversionType": "multiply", "conversionSymbol": "ETH"}, {"time": 1605675840, "high": 0.07372, "low": 0.07372, "open": 0.07373, "volumefrom": 0, "volumeto": 0, "close": 0.07372, "conversionType": "multiply", "conversionSymbol": "ETH"}, {"time": 1605675900, "high": 0.07387, "low": 0.07387, "open": 0.07372, "volumefrom": 0, "volumeto": 0, "close": 0.07387, "conversionType": "multiply", "conversionSymbol": "ETH"}, {"time": 1605675960, "high": 0.07389, "low": 0.07389, "open": 0.07387, "volumefrom": 0, "volumeto": 0, "close": 0.07389, "conversionType": "multiply", "conversionSymbol": "ETH"}, {"time": 1605676020, "high": 0.074, "low": 0.074, "open": 0.07389, "volumefrom": 0, "volumeto": 0, "close": 0.074, "conversionType": "multiply", "conversionSymbol": "ETH"}, {"time": 1605676080, "high": 0.07402, "low": 0.07402, "open": 0.074, "volumefrom": 0, "volumeto": 0, "close": 0.07402, "conversionType": "multiply", "conversionSymbol": "ETH"}, {"time": 1605676140, "high": 0.07402, "low": 0.07402, "open": 0.07402, "volumefrom": 0, "volumeto": 0, "close": 0.07402, "conversionType": "multiply", "conversionSymbol": "ETH"}, {"time": 1605676200, "high": 0.07404, "low": 0.07404, "open": 0.07402, "volumefrom": 0, "volumeto": 0, "close": 0.07404, "conversionType": "multiply", "conversionSymbol": "ETH"}, {"time": 1605676260, "high": 0.07415, "low": 0.07415, "open": 0.07404, "volumefrom": 0, "volumeto": 0, "close": 0.07415, "conversionType": "multiply", "conversionSymbol": "ETH"}, {"time": 1605676320, "high": 0.07417, "low": 0.07417, "open": 0.07415, "volumefrom": 0, "volumeto": 0, "close": 0.07417, "conversionType": "multiply", "conversionSymbol": "ETH"}, {"time": 1605676380, "high": 0.07417, "low": 0.07417, "open": 0.07417, "volumefrom": 0, "volumeto": 0, "close": 0.07417, "conversionType": "multiply", "conversionSymbol": "ETH"}, {"time": 1605676440, "high": 0.07419, "low": 0.07419, "open": 0.07417, "volumefrom": 0, "volumeto": 0, "close": 0.07419, "conversionType": "multiply", "conversionSymbol": "ETH"}, {"time": 1605676500, "high": 0.07408, "low": 0.07408, "open": 0.07419, "volumefrom": 0, "volumeto": 0, "close": 0.07408, "conversionType": "multiply", "conversionSymbol": "ETH"}, {"time": 1605676560, "high": 0.07411, "low": 0.07411, "open": 0.07408, "volumefrom": 0, "volumeto": 0, "close": 0.07411, "conversionType": "multiply", "conversionSymbol": "ETH"}, {"time": 1605676620, "high": 0.07416, "low": 0.07416, "open": 0.07411, "volumefrom": 0, "volumeto": 0, "close": 0.07416, "conversionType": "multiply", "conversionSymbol": "ETH"}, {"time": 1605676680, "high": 0.07404, "low": 0.07404, "open": 0.07416, "volumefrom": 0, "volumeto": 0, "close": 0.07404, "conversionType": "multiply", "conversionSymbol": "ETH"}, {"time": 1605676740, "high": 0.074, "low": 0.074, "open": 0.07404, "volumefrom": 0, "volumeto": 0, "close": 0.074, "conversionType": "multiply", "conversionSymbol": "ETH"}, {"time": 1605676800, "high": 0.07394, "low": 0.07394, "open": 0.074, "volumefrom": 0, "volumeto": 0, "close": 0.07394, "conversionType": "multiply", "conversionSymbol": "ETH"}, {"time": 1605676860, "high": 0.07394, "low": 0.07394, "open": 0.07394, "volumefrom": 0, "volumeto": 0, "close": 0.07394, "conversionType": "multiply", "conversionSymbol": "ETH"}, {"time": 1605676920, "high": 0.07396, "low": 0.07396, "open": 0.07394, "volumefrom": 0, "volumeto": 0, "close": 0.07396, "conversionType": "multiply", "conversionSymbol": "ETH"}, {"time": 1605676980, "high": 0.07399, "low": 0.07399, "open": 0.07396, "volumefrom": 0, "volumeto": 0, "close": 0.07399, "conversionType": "multiply", "conversionSymbol": "ETH"}]