[{"time": 1603065600, "high": 0.6089, "low": 0.6089, "open": 0.5963, "volumefrom": 0, "volumeto": 0, "close": 0.6089, "conversionType": "multiply", "conversionSymbol": "BTC"}, {"time": 1603152000, "high": 0.6174, "low": 0.6174, "open": 0.6089, "volumefrom": 0, "volumeto": 0, "close": 0.6174, "conversionType": "multiply", "conversionSymbol": "BTC"}, {"time": 1603238400, "high": 0.6636, "low": 0.6636, "open": 0.6174, "volumefrom": 0, "volumeto": 0, "close": 0.6636, "conversionType": "multiply", "conversionSymbol": "BTC"}, {"time": 1603324800, "high": 0.6728, "low": 0.6728, "open": 0.6636, "volumefrom": 0, "volumeto": 0, "close": 0.6728, "conversionType": "multiply", "conversionSymbol": "BTC"}, {"time": 1603411200, "high": 0.67, "low": 0.67, "open": 0.6728, "volumefrom": 0, "volumeto": 0, "close": 0.67, "conversionType": "multiply", "conversionSymbol": "BTC"}, {"time": 1603497600, "high": 0.6798, "low": 0.6798, "open": 0.67, "volumefrom": 0, "volumeto": 0, "close": 0.6798, "conversionType": "multiply", "conversionSymbol": "BTC"}, {"time": 1603584000, "high": 0.6754, "low": 0.6754, "open": 0.6798, "volumefrom": 0, "volumeto": 0, "close": 0.6754, "conversionType": "multiply", "conversionSymbol": "BTC"}, {"time": 1603670400, "high": 0.6769, "low": 0.6769, "open": 0.6754, "volumefrom": 0, "volumeto": 0, "close": 0.6769, "conversionType": "multiply", "conversionSymbol": "BTC"}, {"time": 1603756800, "high": 0.7067, "low": 0.7067, "open": 0.6769, "volumefrom": 0, "volumeto": 0, "close": 0.7067, "conversionType": "multiply", "conversionSymbol": "BTC"}, {"time": 1603843200, "high": 0.6881, "low": 0.6881, "open": 0.7067, "volumefrom": 0, "volumeto": 0, "close": 0.6881, "conversionType": "multiply", "conversionSymbol": "BTC"}, {"time": 1603929600, "high": 0.6972, "low": 0.6972, "open": 0.6881, "volumefrom": 0, "volumeto": 0, "close": 0.6972, "conversionType": "multiply", "conversionSymbol": "BTC"}, {"time": 1604016000, "high": 0.7026, "low": 0.7026, "open": 0.6972, "volumefrom": 0, "volumeto": 0, "close": 0.7026, "conversionType": "multiply", "conversionSymbol": "BTC"}, {"time": 1604102400, "high": 0.7149, "low": 0.7149, "open": 0.7026, "volumefrom": 0, "volumeto": 0, "close": 0.7149, "conversionType": "multiply", "conversionSymbol": "BTC"}, {"time": 1604188800, "high": 0.7127, "low": 0.7127, "open": 0.7149, "volumefrom": 0, "volumeto": 0, "close": 0.7127, "conversionType": "multiply", "conversionSymbol": "BTC"}, {"time": 1604275200, "high": 0.7029, "low": 0.7029, "open": 0.7127, "volumefrom": 0, "volumeto": 0, "close": 0.7029, "conversionType": "multiply", "conversionSymbol": "BTC"}, {"time": 1604361600, "high": 0.7263, "low": 0.7263, "open": 0.7029, "volumefrom": 0, "volumeto": 0, "close": 0.7263, "conversionType": "multiply", "conversionSymbol": "BTC"}, {"time": 1604448000, "high": 0.7332, "low": 0.7332, "open": 0.7263, "volumefrom": 0, "volumeto": 0, "close": 0.7332, "conversionType": "multiply", "conversionSymbol": "BTC"}, {"time": 1604534400, "high": 0.8079, "low": 0.8079, "open": 0.7332, "volumefrom": 0, "volumeto": 0, "close": 0.8079, "conversionType": "multiply", "conversionSymbol": "BTC"}, {"time": 1604620800, "high": 0.8074, "low": 0.8074, "open": 0.8079, "volumefrom": 0, "volumeto": 0, "close": 0.8074, "conversionType": "multiply", "conversionSymbol": "BTC"}, {"time": 1604707200, "high": 0.7685, "low": 0.7685, "open": 0.8074, "volumefrom": 0, "volumeto": 0, "close": 0.7685, "conversionType": "multiply", "conversionSymbol": "BTC"}, {"time": 1604793600, "high": 0.8021, "low": 0.8021, "open": 0.7685, "volumefrom": 0, "volumeto": 0, "close": 0.8021, "conversionType": "multiply", "conversionSymbol": "BTC"}, {"time": 1604880000, "high": 0.7942, "low": 0.7942, "open": 0.8021, "volumefrom": 0, "volumeto": 0, "close": 0.7942, "conversionType": "multiply", "conversionSymbol": "BTC"}, {"time": 1604966400, "high": 0.7931, "low": 0.7931, "open": 0.7942, "volumefrom": 0, "volumeto": 0, "close": 0.7931, "conversionType": "multiply", "conversionSymbol": "BTC"}, {"time": 1605052800, "high": 0.8135, "low": 0.8135, "open": 0.7931, "volumefrom": 0, "volumeto": 0, "close": 0.8135, "conversionType": "multiply", "conversionSymbol": "BTC"}, {"time": 1605139200, "high": 0.8445, "low": 0.8445, "open": 0.8135, "volumefrom": 0, "volumeto": 0, "close": 0.8445, "conversionType": "multiply", "conversionSymbol": "BTC"}, {"time": 1605225600, "high": 0.8459, "low": 0.8459, "open": 0.8445, "volumefrom": 0, "volumeto": 0, "close": 0.8459, "conversionType": "multiply", "conversionSymbol": "BTC"}, {"time": 1605312000, "high": 0.8326, "low": 0.8326, "open": 0.8459, "volumefrom": 0, "volumeto": 0, "close": 0.8326, "conversionType": "multiply", "conversionSymbol": "BTC"}, {"time": 1605398400, "high": 0.8268, "low": 0.8268, "open": 0.8326, "volumefrom": 0, "volumeto": 0, "close": 0.8268, "conversionType": "multiply", "conversionSymbol": "BTC"}, {"time": 1605484800, "high": 0.866, "low": 0.866, "open": 0.8268, "volumefrom": 0, "volumeto": 0, "close": 0.866, "conversionType": "multiply", "conversionSymbol": "BTC"}, {"time": 1605571200, "high": 0.9157, "low": 0.9157, "open": 0.866, "volumefrom": 0, "volumeto": 0, "close": 0.9157, "conversionType": "multiply", "conversionSymbol": "BTC"}, {"time": 1605657600, "high": 0.9157, "low": 0.003652, "open": 0.9157, "volumefrom": 0, "volumeto": 0, "close": 0.003652, "conversionType": "multiply", "conversionSymbol": "BTC"}]