[{"time": 1603065600, "high": 0.001528, "low": 0.001528, "open": 0.001497, "volumefrom": 0, "volumeto": 0, "close": 0.001528, "conversionType": "multiply", "conversionSymbol": "BTC"}, {"time": 1603152000, "high": 0.00155, "low": 0.00155, "open": 0.001528, "volumefrom": 0, "volumeto": 0, "close": 0.00155, "conversionType": "multiply", "conversionSymbol": "BTC"}, {"time": 1603238400, "high": 0.001666, "low": 0.001666, "open": 0.00155, "volumefrom": 0, "volumeto": 0, "close": 0.001666, "conversionType": "multiply", "conversionSymbol": "BTC"}, {"time": 1603324800, "high": 0.001689, "low": 0.001689, "open": 0.001666, "volumefrom": 0, "volumeto": 0, "close": 0.001689, "conversionType": "multiply", "conversionSymbol": "BTC"}, {"time": 1603411200, "high": 0.001682, "low": 0.001682, "open": 0.001689, "volumefrom": 0, "volumeto": 0, "close": 0.001682, "conversionType": "multiply", "conversionSymbol": "BTC"}, {"time": 1603497600, "high": 0.001706, "low": 0.001706, "open": 0.001682, "volumefrom": 0, "volumeto": 0, "close": 0.001706, "conversionType": "multiply", "conversionSymbol": "BTC"}, {"time": 1603584000, "high": 0.001695, "low": 0.001695, "open": 0.001706, "volumefrom": 0, "volumeto": 0, "close": 0.001695, "conversionType": "multiply", "conversionSymbol": "BTC"}, {"time": 1603670400, "high": 0.001699, "low": 0.001699, "open": 0.001695, "volumefrom": 0, "volumeto": 0, "close": 0.001699, "conversionType": "multiply", "conversionSymbol": "BTC"}, {"time": 1603756800, "high": 0.001774, "low": 0.001774, "open": 0.001699, "volumefrom": 0, "volumeto": 0, "close": 0.001774, "conversionType": "multiply", "conversionSymbol": "BTC"}, {"time": 1603843200, "high": 0.001727, "low": 0.001727, "open": 0.001774, "volumefrom": 0, "volumeto": 0, "close": 0.001727, "conversionType": "multiply", "conversionSymbol": "BTC"}, {"time": 1603929600, "high": 0.00175, "low": 0.00175, "open": 0.001727, "volumefrom": 0, "volumeto": 0, "close": 0.00175, "conversionType": "multiply", "conversionSymbol": "BTC"}, {"time": 1604016000, "high": 0.001764, "low": 0.001764, "open": 0.00175, "volumefrom": 0, "volumeto": 0, "close": 0.001764, "conversionType": "multiply", "conversionSymbol": "BTC"}, {"time": 1604102400, "high": 0.001794, "low": 0.001794, "open": 0.001764, "volumefrom": 0, "volumeto": 0, "close": 0.001794, "conversionType": "multiply", "conversionSymbol": "BTC"}, {"time": 1604188800, "high": 0.001789, "low": 0.001789, "open": 0.001794, "volumefrom": 0, "volumeto": 0, "close": 0.001789, "conversionType": "multiply", "conversionSymbol": "BTC"}, {"time": 1604275200, "high": 0.001764, "low": 0.001764, "open": 0.001789, "volumefrom": 0, "volumeto": 0, "close": 0.001764, "conversionType": "multiply", "conversionSymbol": "BTC"}, {"time": 1604361600, "high": 0.001823, "low": 0.001823, "open": 0.001764, "volumefrom": 0, "volumeto": 0, "close": 0.001823, "conversionType": "multiply", "conversionSymbol": "BTC"}, {"time": 1604448000, "high": 0.001841, "low": 0.001841, "open": 0.001823, "volumefrom": 0, "volumeto": 0, "close": 0.001841, "conversionType": "multiply", "conversionSymbol": "BTC"}, {"time": 1604534400, "high": 0.002028, "low": 0.002028, "open": 0.001841, "volumefrom": 0, "volumeto": 0, "close": 0.002028, "conversionType": "multiply", "conversionSymbol": "BTC"}, {"time": 1604620800, "high": 0.002027, "low": 0.002027, "open": 0.002028, "volumefrom": 0, "volumeto": 0, "close": 0.002027, "conversionType": "multiply", "conversionSymbol": "BTC"}, {"time": 1604707200, "high": 0.001929, "low": 0.001929, "open": 0.002027, "volumefrom": 0, "volumeto": 0, "close": 0.001929, "conversionType": "multiply", "conversionSymbol": "BTC"}, {"time": 1604793600, "high": 0.002013, "low": 0.002013, "open": 0.001929, "volumefrom": 0, "volumeto": 0, "close": 0.002013, "conversionType": "multiply", "conversionSymbol": "BTC"}, {"time": 1604880000, "high": 0.001994, "low": 0.001994, "open": 0.002013, "volumefrom": 0, "volumeto": 0, "close": 0.001994, "conversionType": "multiply", "conversionSymbol": "BTC"}, {"time": 1604966400, "high": 0.001991, "low": 0.001991, "open": 0.001994, "volumefrom": 0, "volumeto": 0, "close": 0.001991, "conversionType": "multiply", "conversionSymbol": "BTC"}, {"time": 1605052800, "high": 0.002042, "low": 0.002042, "open": 0.001991, "volumefrom": 0, "volumeto": 0, "close": 0.002042, "conversionType": "multiply", "conversionSymbol": "BTC"}, {"time": 1605139200, "high": 0.00212, "low": 0.00212, "open": 0.002042, "volumefrom": 0, "volumeto": 0, "close": 0.00212, "conversionType": "multiply", "conversionSymbol": "BTC"}, {"time": 1605225600, "high": 0.002123, "low": 0.002123, "open": 0.00212, "volumefrom": 0, "volumeto": 0, "close": 0.002123, "conversionType": "multiply", "conversionSymbol": "BTC"}, {"time": 1605312000, "high": 0.00209, "low": 0.00209, "open": 0.002123, "volumefrom": 0, "volumeto": 0, "close": 0.00209, "conversionType": "multiply", "conversionSymbol": "BTC"}, {"time": 1605398400, "high": 0.002075, "low": 0.002075, "open": 0.00209, "volumefrom": 0, "volumeto": 0, "close": 0.002075, "conversionType": "multiply", "conversionSymbol": "BTC"}, {"time": 1605484800, "high": 0.002174, "low": 0.002174, "open": 0.002075, "volumefrom": 0, "volumeto": 0, "close": 0.002174, "conversionType": "multiply", "conversionSymbol": "BTC"}, {"time": 1605571200, "high": 0.002299, "low": 0.002299, "open": 0.002174, "volumefrom": 0, "volumeto": 0, "close": 0.002299, "conversionType": "multiply", "conversionSymbol": "BTC"}, {"time": 1605657600, "high": 0.008582, "low": 0.002299, "open": 0.002299, "volumefrom": 0, "volumeto": 0, "close": 0.008582, "conversionType": "multiply", "conversionSymbol": "BTC"}]